setup.py
django_freshly.egg-info/PKG-INFO
django_freshly.egg-info/SOURCES.txt
django_freshly.egg-info/dependency_links.txt
django_freshly.egg-info/top_level.txt
freshly/__init__.py
freshly/defaults.py
freshly/middleware/__init__.py
freshly/middleware/assets.py
freshly/tests/__init__.py
freshly/tests/tests.py
freshly/tests/testsettings.py