Metadata-Version: 1.1
Name: django-freshly
Version: 0.1.2
Summary: A Django application that enables your server to remotely trigger assets reload by the client(s)
Home-page: https://github.com/un33k/django-freshly
Author: Val Neekman
Author-email: info@neekware.com
License: BSD
Platform: UNKNOWN
Classifier: Development Status :: 4 - Beta
Classifier: Environment :: Web Environment
Classifier: Intended Audience :: Developers
Classifier: License :: OSI Approved :: BSD License
Classifier: Operating System :: OS Independent
Classifier: Programming Language :: Python
Classifier: Topic :: Utilities
